fourinsight/engineroom/utils/__init__.py
fourinsight/engineroom/utils/_constants.py
fourinsight/engineroom/utils/_core.py
fourinsight/engineroom/utils/_datamanage.py
fourinsight/engineroom/utils/iter_index/__init__.py
fourinsight/engineroom/utils/iter_index/_iter_index.py
fourinsight_engineroom_utils-0.7.7.dist-info/licenses/LICENSE
fourinsight_engineroom_utils-0.7.7.dist-info/METADATA
fourinsight_engineroom_utils-0.7.7.dist-info/WHEEL
fourinsight_engineroom_utils-0.7.7.dist-info/top_level.txt
fourinsight_engineroom_utils-0.7.7.dist-info/RECORD
